verysimplemodule/__init__.py
verysimplemodule/add.py
verysimplemodule/substract.py
verysimplemodule/extras/__init__.py
verysimplemodule/extras/divide.py
verysimplemodule/extras/multiply.py
verysimplemodulebyfmg/__init__.py
verysimplemodulebyfmg/add.py
verysimplemodulebyfmg/substract.py
verysimplemodulebyfmg/extras/__init__.py
verysimplemodulebyfmg/extras/divide.py
verysimplemodulebyfmg/extras/multiply.py
verysimplemodulebyfmg-0.0.5.dist-info/METADATA
verysimplemodulebyfmg-0.0.5.dist-info/WHEEL
verysimplemodulebyfmg-0.0.5.dist-info/top_level.txt
verysimplemodulebyfmg-0.0.5.dist-info/RECORD
