Metadata-Version: 2.1
Name: verysimplemodulebyfmg
Version: 0.0.5
Summary: My first Python package
Author: Fatih GENÇ
Author-email: f.genc@qimia.de
Keywords: python,first package
Classifier: Development Status :: 3 - Alpha
Classifier: Intended Audience :: Education
Classifier: Programming Language :: Python :: 2
Classifier: Programming Language :: Python :: 3
Classifier: Operating System :: MacOS :: MacOS X
Classifier: Operating System :: Microsoft :: Windows
